meta_tags_parser/__init__.py
meta_tags_parser/download.py
meta_tags_parser/parse.py
meta_tags_parser/public.py
meta_tags_parser/py.typed
meta_tags_parser/settings.py
meta_tags_parser/snippets.py
meta_tags_parser/structs.py
meta_tags_parser-1.3.0.dist-info/LICENSE
meta_tags_parser-1.3.0.dist-info/METADATA
meta_tags_parser-1.3.0.dist-info/WHEEL
meta_tags_parser-1.3.0.dist-info/RECORD
