Metadata-Version: 2.1
Name: meta-tags-parser
Version: 1.3.0
Summary: Fast and modern meta tags parser (og, twitter, title, description, etc) with snippet support
Home-page: https://github.com/xfenix/meta-tags-parser/
License: MIT
Author: Denis Anikin
Author-email: ad@xfenix.ru
Requires-Python: >=3.8,<4.0
Classifier: License :: OSI Approved :: MIT License
Classifier: Programming Language :: Python :: 3
Classifier: Programming Language :: Python :: 3.8
Classifier: Programming Language :: Python :: 3.9
Classifier: Programming Language :: Python :: 3.10
Classifier: Programming Language :: Python :: 3.11
Classifier: Topic :: Software Development :: Libraries :: Python Modules
Requires-Dist: httpx
Project-URL: Documentation, https://github.com/xfenix/meta-tags-parser
